zephflow/__init__.py
zephflow/__main__.py
zephflow/core.py
zephflow/jar_manager.py
zephflow/job_context.py
zephflow/py.typed
zephflow/utils.py
zephflow/versions.py
zephflow-0.3.1.dist-info/METADATA
zephflow-0.3.1.dist-info/WHEEL
zephflow-0.3.1.dist-info/licenses/LICENSE
zephflow-0.3.1.dist-info/RECORD
