Metadata-Version: 2.4
Name: zephflow
Version: 0.3.1
Summary: Python SDK for ZephFlow data processing pipelines
License: Apache-2.0
License-File: LICENSE
Keywords: data-processing,streaming,etl,pipeline,workflow
Author: Fleak Tech Inc.
Author-email: contact@fleak.ai
Requires-Python: >=3.8.1,<4.0.0
Classifier: Development Status :: 4 - Beta
Classifier: Intended Audience :: Developers
Classifier: License :: OSI Approved :: Apache Software License
Classifier: Programming Language :: Python :: 3
Classifier: Programming Language :: Python :: 3.9
Classifier: Programming Language :: Python :: 3.10
Classifier: Programming Language :: Python :: 3.11
Classifier: Programming Language :: Python :: 3.12
Classifier: Programming Language :: Python :: 3.13
Classifier: Programming Language :: Python :: 3.14
Classifier: Programming Language :: Python :: 3.8
Classifier: Topic :: Software Development :: Libraries :: Python Modules
Classifier: Topic :: System :: Distributed Computing
Requires-Dist: py4j (>=0.10.9.7,<0.11.0.0)
Requires-Dist: requests (>=2.32.0,<3.0.0)
Project-URL: Documentation, https://docs.fleak.ai/zephflow
Project-URL: Homepage, https://github.com/fleaktech/zephflow-python-sdk
Project-URL: Repository, https://github.com/fleaktech/zephflow-python-sdk
